alphax/__init__.py
alphax/robot.py
alphax_robot-0.0.1.1.dist-info/LICENCE.txt
alphax_robot-0.0.1.1.dist-info/METADATA
alphax_robot-0.0.1.1.dist-info/WHEEL
alphax_robot-0.0.1.1.dist-info/top_level.txt
alphax_robot-0.0.1.1.dist-info/RECORD
