Metadata-Version: 2.1
Name: alphax-robot
Version: 0.0.1.1
Summary: Python library to control an AlphaX robot
Home-page: https://github.com/VanThanBK/python-alphax
Author: Than Nguyen
Author-email: jonyvanthan@gmail.com
License: UNKNOWN
Project-URL: Bug Tracker, https://github.com/VanThanBK/python-alphax
Platform: UNKNOWN
Classifier: Programming Language :: Python :: 3
Classifier: License :: OSI Approved :: MIT License
Classifier: Operating System :: OS Independent
Requires-Python: >=3.6
License-File: LICENCE.txt
